[
  {
    "id": "38795d07-fbf2-4e82-ad55-f151253c35fd",
    "title": "statementOfEnvironmentalEffects - 96 Francis Avenue Brighton-le-sands",
    "path": "work-tickets/36be2253-d2a1-419f-ba0d-2810999918e9",
    "type": "document",
    "category": "REPORTS",
    "versions": [],
    "currentVersion": 1,
    "createdAt": "2025-05-12T10:27:04.535Z",
    "updatedAt": "2025-05-12T10:27:04.535Z",
    "isActive": true,
    "metadata": {
      "jobId": "a8a2f689-5039-4da3-9e8b-c350b963f3cf",
      "ticketId": "36be2253-d2a1-419f-ba0d-2810999918e9",
      "ticketType": "statementOfEnvironmentalEffects",
      "attachedDocuments": {
        "certificateOfTitle": {},
        "surveyPlan": {},
        "certificate107": {
          "originalName": "10.7 Certificate Check.pdf",
          "fileName": "tenSevenCertificate_1747045608867_10.7 Certificate Check.pdf"
        }
      },
      "jobAddress": "96 Francis Avenue Brighton-le-sands",
      "uploadedBy": "professional",
      "reportData": {
        "developmentType": "123",
        "additionalInfo": "456",
        "documents": {
          "certificateOfTitle": {},
          "surveyPlan": {},
          "certificate107": {
            "originalName": "10.7 Certificate Check.pdf",
            "fileName": "tenSevenCertificate_1747045608867_10.7 Certificate Check.pdf"
          }
        }
      }
    },
    "displayStatus": "pending_admin_delivery"
  }
]